graph_rl/__init__.py
graph_rl/algorithms/__init__.py
graph_rl/algorithms/algorithm.py
graph_rl/algorithms/goal_sampling_strategy.py
graph_rl/algorithms/hac.py
graph_rl/algorithms/hits.py
graph_rl/algorithms/off_policy_algorithm.py
graph_rl/aux_rewards/__init__.py
graph_rl/aux_rewards/aux_reward.py
graph_rl/aux_rewards/constant_reward.py
graph_rl/aux_rewards/delta_t_ach_reward.py
graph_rl/aux_rewards/env_reward.py
graph_rl/aux_rewards/goal_tol_reward.py
graph_rl/aux_rewards/power_reward.py
graph_rl/data/__init__.py
graph_rl/data/env_info.py
graph_rl/data/flat_transition.py
graph_rl/data/parent_info.py
graph_rl/data/segmented_replay_buffer.py
graph_rl/data/sess_info.py
graph_rl/data/subtask_transition.py
graph_rl/envs/__init__.py
graph_rl/envs/dummy_env.py
graph_rl/envs/flatten_wrapper.py
graph_rl/envs/graphics_utils.py
graph_rl/envs/obstacle_env.py
graph_rl/envs/pyglet_utils.py
graph_rl/global_algorithms/__init__.py
graph_rl/global_algorithms/global_algorithm.py
graph_rl/graphs/__init__.py
graph_rl/graphs/graph.py
graph_rl/graphs/hac_graph.py
graph_rl/graphs/hits_graph.py
graph_rl/logging/__init__.py
graph_rl/logging/csv_logger.py
graph_rl/models/__init__.py
graph_rl/models/ddpg_model.py
graph_rl/models/mlp_actor_critic_model.py
graph_rl/models/model.py
graph_rl/models/sac_model.py
graph_rl/networks/__init__.py
graph_rl/networks/concat_network.py
graph_rl/networks/ddpg_network.py
graph_rl/networks/mlp_network.py
graph_rl/networks/negative_network.py
graph_rl/networks/sac_network.py
graph_rl/networks/squash_network.py
graph_rl/nodes/__init__.py
graph_rl/nodes/hac_node.py
graph_rl/nodes/hits_node.py
graph_rl/nodes/node.py
graph_rl/policies/__init__.py
graph_rl/policies/policy.py
graph_rl/policies/tianshou_policy.py
graph_rl/session/__init__.py
graph_rl/session/session.py
graph_rl/spaces/__init__.py
graph_rl/spaces/binary_space.py
graph_rl/spaces/box_space.py
graph_rl/spaces/dict_space.py
graph_rl/spaces/gym_conv_dict.py
graph_rl/spaces/multi_binary_space.py
Graph_RL-0.1.2.dist-info/LICENSE.txt
Graph_RL-0.1.2.dist-info/METADATA
Graph_RL-0.1.2.dist-info/WHEEL
Graph_RL-0.1.2.dist-info/top_level.txt
Graph_RL-0.1.2.dist-info/RECORD
