Metadata-Version: 2.1
Name: Graph-RL
Version: 0.1.2
Summary: Hierarchical reinforcement learning framework which uses a directed graph to define the hierarchy.
Home-page: https://github.com/nicoguertler/graph_rl
Author: Nico Gürtler
Author-email: nico.guertler@tuebingen.mpg.de
License: MIT
Keywords: reinforcement learning,hierarchical reinforcement learning
Platform: UNKNOWN
Requires-Dist: dyn-rl-benchmarks
Requires-Dist: gym (==0.21.0)
Requires-Dist: numpy
Requires-Dist: pyglet
Requires-Dist: tianshou (==0.3.1)
